telegram_export/__init__.py
telegram_export/__main__.py
telegram_export/downloader.py
telegram_export/dumper.py
telegram_export/exporter.py
telegram_export/tests.py
telegram_export/utils.py
telegram_export/formatters/__init__.py
telegram_export/formatters/baseformatter.py
telegram_export/formatters/htmlformatter.py
telegram_export/formatters/nlpformatter.py
telegram_export/formatters/textformatter.py
telegram_export/tests/__init__.py
telegram_export/tests/test_utils.py
telegram_export-1.8.2.data/scripts/telegram-export
telegram_export-1.8.2.dist-info/LICENSE
telegram_export-1.8.2.dist-info/METADATA
telegram_export-1.8.2.dist-info/WHEEL
telegram_export-1.8.2.dist-info/top_level.txt
telegram_export-1.8.2.dist-info/RECORD
