Metadata-Version: 1.1
Name: telegram-export
Version: 1.8.2
Summary: A tool to download Telegram data (users, chats, messages, and media) into a database (and display the saved data).
Home-page: https://github.com/expectocode/telegram-export
Author: expectocode and Lonami
Author-email: expectocode@gmail.com
License: MPL 2.0
Project-URL: Bug Reports, https://github.com/expectocode/telegram-export/issues
Project-URL: Source, https://github.com/expectocode/telegram-export
Keywords: Telegram messaging database
Platform: UNKNOWN
Classifier: Development Status :: 4 - Beta
Classifier: Intended Audience :: Developers
Classifier: License :: OSI Approved :: Mozilla Public License 2.0 (MPL 2.0)
Classifier: Programming Language :: Python :: 3
